{
    "swagger": "2.0",
    "info": {
        "contact": {}
    },
    "paths": {
        "/": {
            "get": {
                "description": "This is a sample server Petstore server.",
                "produces": [
                    "application/json"
                ],
                "summary": "打印测试功能",
                "parameters": [
                    {
                        "type": "string",
                        "description": "Name",
                        "name": "name",
                        "in": "query",
                        "required": true
                    }
                ],
                "responses": {
                    "200": {
                        "description": "{\"code\":200,\"data\":\"name\",\"msg\":\"ok\"}",
                        "schema": {
                            "type": "string"
                        }
                    }
                }
            }
        }
    }
}